AUTHORS.rst
CONTRIBUTING.rst
HISTORY.rst
LICENSE
MANIFEST.in
README.rst
setup.py
dns_failover/__init__.py
dns_failover/backends.py
dns_failover/core.py
python_dns_failover.egg-info/PKG-INFO
python_dns_failover.egg-info/SOURCES.txt
python_dns_failover.egg-info/dependency_links.txt
python_dns_failover.egg-info/not-zip-safe
python_dns_failover.egg-info/requires.txt
python_dns_failover.egg-info/top_level.txt