Metadata-Version: 1.1
Name: python-dns-failover
Version: 0.1.0
Summary: "Python script to automatically update DNS records for a bunch of servers participating in a Round-Robin DNS setup"
Home-page: https://github.com/marccerrato/python-dns-failover
Author: Marc Cerrato
Author-email: marccerrato@gmail.com
License: BSD
Keywords: python-dns-failover
Platform: UNKNOWN
Classifier: Development Status :: 2 - Pre-Alpha
Classifier: Intended Audience :: Developers
Classifier: License :: OSI Approved :: BSD License
Classifier: Natural Language :: English
Classifier: Programming Language :: Python :: 2
Classifier: Programming Language :: Python :: 2.6
Classifier: Programming Language :: Python :: 2.7
Classifier: Programming Language :: Python :: 3
Classifier: Programming Language :: Python :: 3.3
